{"nodes": [{"id": "middlewares_api_route_registry", "label": "API Route Registry", "file_type": "code", "source_file": "backend/src/api/middlewares.ts", "source_location": null, "source_url": null, "captured_at": null, "author": null, "contributor": null}], "edges": [{"source": "middlewares_api_route_registry", "target": "middlewares_admin_page_validation", "relation": "references", "confidence": "EXTRACTED", "confidence_score": 1.0, "source_file": "backend/src/api/middlewares.ts", "source_location": null, "weight": 1.0}, {"source": "middlewares_api_route_registry", "target": "middlewares_store_page_query_validation", "relation": "references", "confidence": "EXTRACTED", "confidence_score": 1.0, "source_file": "backend/src/api/middlewares.ts", "source_location": null, "weight": 1.0}], "hyperedges": []}